{
  "schema": "TESSERA-EVO-023-MODE-AUDIT-PREREGISTRATION-v0.1",
  "operation": "TESSERA-EVO-023",
  "cohort": "outputs/evidence/evo021/natural_split_calibration.json",
  "chronological_split": {
    "discovery_sessions": 20,
    "validation_sessions": 20
  },
  "tail_definition": {
    "robust_score_threshold": 6.0,
    "minimum_scale_ms": 5.0
  },
  "candidate_mode_requirements": {
    "minimum_discovery_support": 3,
    "minimum_validation_support": 3,
    "same_tail_phase_signature_required": true
  },
  "decision_rule": "Reject mode separation unless a phase-tail signature satisfies every support and recurrence requirement.",
  "prohibited_actions": [
    "remove valid slow sessions from calibration",
    "lower threshold using confirmation outcomes",
    "label isolated tail sessions as failures",
    "claim production incident modes"
  ],
  "claim_boundary": "The audit tests recurrence of privacy-safe latency patterns only; it does not diagnose causes or authorize calibration changes."
}
